f5py-0.3.0.dist-info/METADATA
f5py-0.3.0.dist-info/WHEEL
f5py/__init__.py
f5py/f5py.pypy37-pp73-aarch64-linux-gnu.so
f5py-0.3.0.dist-info/RECORD
