Metadata-Version: 2.1
Name: f5py
Version: 0.3.0
Summary: F5 BIG-IP Parser and Config Generator written in Rust
Keywords: f5,big-ip,parser,rust,load balancer,applications delivery controller,config,generator,ADC,cisco,juniper
Home-Page: https://ipvx.me/f5
Author: Ahmed Thabet <eng@AhmedThabet.com>
Author-email: Ahmed Thabet <eng@AhmedThabet.com>
Project-URL: Source Code, https://github.com/AhmedThabet/f5py-doc
